odoo/addons/l10n_be_cooperator/README.rst
odoo/addons/l10n_be_cooperator/__init__.py
odoo/addons/l10n_be_cooperator/__manifest__.py
odoo/addons/l10n_be_cooperator/data/mail_template_data.xml
odoo/addons/l10n_be_cooperator/data/scheduler_data.xml
odoo/addons/l10n_be_cooperator/demo/tax_shelter_demo.xml
odoo/addons/l10n_be_cooperator/i18n/fr_BE.po
odoo/addons/l10n_be_cooperator/i18n/it.po
odoo/addons/l10n_be_cooperator/i18n/l10n_be_cooperator.pot
odoo/addons/l10n_be_cooperator/migrations/14.0.1.2.2/pre-migrate.py
odoo/addons/l10n_be_cooperator/models/__init__.py
odoo/addons/l10n_be_cooperator/models/partner.py
odoo/addons/l10n_be_cooperator/models/subscription_request.py
odoo/addons/l10n_be_cooperator/models/tax_shelter_declaration.py
odoo/addons/l10n_be_cooperator/readme/CONTRIBUTORS.rst
odoo/addons/l10n_be_cooperator/readme/DESCRIPTION.rst
odoo/addons/l10n_be_cooperator/reports/tax_shelter_report.xml
odoo/addons/l10n_be_cooperator/reports/tax_shelter_resold_report.xml
odoo/addons/l10n_be_cooperator/reports/tax_shelter_shares_report.xml
odoo/addons/l10n_be_cooperator/reports/tax_shelter_subscription_report.xml
odoo/addons/l10n_be_cooperator/security/ir.model.access.csv
odoo/addons/l10n_be_cooperator/static/description/icon.png
odoo/addons/l10n_be_cooperator/static/description/index.html
odoo/addons/l10n_be_cooperator/tests/__init__.py
odoo/addons/l10n_be_cooperator/tests/test_tax_shelter.py
odoo/addons/l10n_be_cooperator/views/subscription_template.xml
odoo/addons/l10n_be_cooperator/views/tax_shelter_declaration_view.xml
odoo14_addon_l10n_be_cooperator-14.0.1.2.7.dist-info/METADATA
odoo14_addon_l10n_be_cooperator-14.0.1.2.7.dist-info/WHEEL
odoo14_addon_l10n_be_cooperator-14.0.1.2.7.dist-info/top_level.txt
odoo14_addon_l10n_be_cooperator-14.0.1.2.7.dist-info/RECORD
